berhoel/get_comics/.__init__.py.~undo-tree~
berhoel/get_comics/__init__.py
"berhoel/get_comics/__init__.py,cover"
berhoel/get_comics/__main__.py
"berhoel/get_comics/_version.py,cover"
berhoel/get_comics/garfield/.__init__.py.~undo-tree~
berhoel/get_comics/garfield/__init__.py
"berhoel/get_comics/garfield/__init__.py,cover"
berhoel/get_comics/garfield/__main__.py
berhoel/get_comics/gen_pdf/.__init__.py.~undo-tree~
berhoel/get_comics/gen_pdf/__init__.py
"berhoel/get_comics/gen_pdf/__init__.py,cover"
berhoel/get_comics/gen_pdf/template/auto/book.el
berhoel/get_comics/gen_pdf/template/auto/book.elc
berhoel/get_comics/gen_pdf/template/book.tex
berhoel/get_comics/gocomics/.__init__.py.~undo-tree~
berhoel/get_comics/gocomics/.mypy_cache/3.8/_ast.data.json
berhoel/get_comics/gocomics/.mypy_cache/3.8/_ast.meta.json
berhoel/get_comics/gocomics/.mypy_cache/3.8/_importlib_modulespec.data.json
berhoel/get_comics/gocomics/.mypy_cache/3.8/_importlib_modulespec.meta.json
berhoel/get_comics/gocomics/.mypy_cache/3.8/abc.data.json
berhoel/get_comics/gocomics/.mypy_cache/3.8/abc.meta.json
berhoel/get_comics/gocomics/.mypy_cache/3.8/ast.data.json
berhoel/get_comics/gocomics/.mypy_cache/3.8/ast.meta.json
berhoel/get_comics/gocomics/.mypy_cache/3.8/types.data.json
berhoel/get_comics/gocomics/.mypy_cache/3.8/types.meta.json
berhoel/get_comics/gocomics/.mypy_cache/3.8/typing.data.json
berhoel/get_comics/gocomics/.mypy_cache/3.8/typing.meta.json.3ab670623ca749ba
berhoel/get_comics/gocomics/__init__.py
"berhoel/get_comics/gocomics/__init__.py,cover"
berhoel/get_comics/peanuts/.__init__.py.~undo-tree~
berhoel/get_comics/peanuts/.clean_up.py.~undo-tree~
berhoel/get_comics/peanuts/.gen_book.py.~undo-tree~
berhoel/get_comics/peanuts/__init__.py
"berhoel/get_comics/peanuts/__init__.py,cover"
berhoel/get_comics/peanuts/__main__.py
berhoel/get_comics/peanuts/clean_up.py
"berhoel/get_comics/peanuts/clean_up.py,cover"
berhoel/get_comics/peanuts/gen_book.py
pygetcomics-1.6.1.dist-info/WHEEL
pygetcomics-1.6.1.dist-info/entry_points.txt
pygetcomics-1.6.1.dist-info/METADATA
pygetcomics-1.6.1.dist-info/RECORD
