Metadata-Version: 2.3
Name: pygetcomics
Version: 1.6.1
Summary: Download various daily comics.
Author: Berthold Höllmann
Author-email: Berthold Höllmann <berthold@xn--hllmanns-n4a.de>
License: BSD-2-Clause
Classifier: Development Status :: 4 - Beta
Classifier: License :: OSI Approved :: BSD License
Classifier: Programming Language :: Python
Classifier: Programming Language :: Python :: Implementation :: CPython
Classifier: Operating System :: OS Independent
Requires-Dist: click
Requires-Dist: pillow
Requires-Dist: lxml
Requires-Dist: requests
Requires-Dist: jinja2
Requires-Dist: playwright
Maintainer: Berthold Höllmann
Maintainer-email: Berthold Höllmann <berthold@xn--hllmanns-n4a.de>
Requires-Python: >=3.13, <4.0
